setup.py
shinkenplugins/__init__.py
shinkenplugins.plugins.drupal_security.egg-info/PKG-INFO
shinkenplugins.plugins.drupal_security.egg-info/SOURCES.txt
shinkenplugins.plugins.drupal_security.egg-info/dependency_links.txt
shinkenplugins.plugins.drupal_security.egg-info/entry_points.txt
shinkenplugins.plugins.drupal_security.egg-info/namespace_packages.txt
shinkenplugins.plugins.drupal_security.egg-info/requires.txt
shinkenplugins.plugins.drupal_security.egg-info/top_level.txt
shinkenplugins/plugins/__init__.py
shinkenplugins/plugins/drupal_security/__init__.py
shinkenplugins/plugins/drupal_security/drupal_security.py